landscape/__init__.py
landscape/peak.py
landscape/visualization.py
seq_landscape-0.1.0b1.dist-info/LICENSE
seq_landscape-0.1.0b1.dist-info/METADATA
seq_landscape-0.1.0b1.dist-info/WHEEL
seq_landscape-0.1.0b1.dist-info/top_level.txt
seq_landscape-0.1.0b1.dist-info/RECORD
