Metadata-Version: 2.1
Name: seq-landscape
Version: 0.1.0b1
Summary: Analysis on sequencing landscape
Home-page: https://github.com/ynshen/Landscape
Author: Yuning Shen
Author-email: ynshen23@gmail.com
License: UNKNOWN
Project-URL: Bug Reports, https://github.com/ynshen/Landscape/issues/
Project-URL: Source, https://github.com/ynshen/Landscape
Platform: UNKNOWN
Classifier: License :: OSI Approved :: MIT License
Requires-Python: >=3.5
Requires-Dist: pandas
Requires-Dist: numpy
Requires-Dist: scipy
Requires-Dist: matplotlib
